ocrd_segment/__init__.py
ocrd_segment/cli.py
ocrd_segment/evaluate.py
ocrd_segment/extract_glyphs.py
ocrd_segment/extract_lines.py
ocrd_segment/extract_pages.py
ocrd_segment/extract_regions.py
ocrd_segment/extract_words.py
ocrd_segment/import_coco_segmentation.py
ocrd_segment/import_image_segmentation.py
ocrd_segment/ocrd-tool.json
ocrd_segment/project.py
ocrd_segment/repair.py
ocrd_segment/replace_original.py
ocrd_segment/replace_page.py
ocrd_segment/replace_text.py
ocrd_segment-0.2.1.dist-info/LICENSE
ocrd_segment-0.2.1.dist-info/METADATA
ocrd_segment-0.2.1.dist-info/WHEEL
ocrd_segment-0.2.1.dist-info/entry_points.txt
ocrd_segment-0.2.1.dist-info/top_level.txt
ocrd_segment-0.2.1.dist-info/RECORD
