Metadata-Version: 2.1
Name: ocrd_segment
Version: 0.2.1
Summary: Page segmentation and segmentation evaluation in the OCR-D framework
Author-email: Kay-Michael Würzner <wuerzner@gmail.com>, Robert Sachunsky <sachunsky@informatik.uni-leipzig.de>, Konstantin Baierer <unixprog@gmail.com>
License: Apache License 2.0
Project-URL: Homepage, https://github.com/OCR-D/ocrd_segment
Project-URL: Repository, https://github.com/OCR-D/ocrd_segment.git
Keywords: ocr,ocr-d
Classifier: Development Status :: 5 - Production/Stable
Classifier: Environment :: Console
Classifier: Intended Audience :: Science/Research
Classifier: Intended Audience :: Other Audience
Classifier: License :: OSI Approved :: Apache Software License
Classifier: Programming Language :: Python :: 3
Classifier: Programming Language :: Python :: 3 :: Only
Classifier: Topic :: Text Processing
Requires-Python: >=3.8
License-File: LICENSE
Requires-Dist: ocrd>=3.0.3
Requires-Dist: shapely>=2.0
Requires-Dist: scikit-image
Requires-Dist: numpy
Requires-Dist: xlsxwriter
Requires-Dist: rapidfuzz
Requires-Dist: opencv-python-headless
Requires-Dist: ocrd-fork-pycocotools
